Ligare/database/__init__.py
Ligare/database/config.py
Ligare/database/dependency_injection.py
Ligare/database/py.typed
Ligare/database/types.py
Ligare/database/engine/__init__.py
Ligare/database/engine/postgresql.py
Ligare/database/engine/sqlite.py
Ligare/database/migrations/__init__.py
Ligare/database/migrations/alembic/README
Ligare/database/migrations/alembic/__init__.py
Ligare/database/migrations/alembic/__main__.py
Ligare/database/migrations/alembic/_replacement_env.py
Ligare/database/migrations/alembic/_replacement_env_setup.py
Ligare/database/migrations/alembic/alembic.ini
Ligare/database/migrations/alembic/env.py
Ligare/database/migrations/alembic/env_setup.py
Ligare/database/migrations/alembic/ligare_alembic.py
Ligare/database/migrations/alembic/script.py.mako
Ligare/database/schema/__init__.py
Ligare/database/schema/dialect.py
Ligare/database/schema/metabase.py
Ligare/database/schema/postgresql.py
Ligare/database/schema/sqlite.py
Ligare/database/testing/__init__.py
Ligare/database/testing/config.py
ligare_database-0.5.1.dist-info/licenses/LICENSE.md
test/unit/test_config.py
test/unit/test_dependency_injection.py
test/unit/test_engine.py
test/unit/test_schema.py
test/unit/migrations/alembic/test_env.py
test/unit/migrations/alembic/test_ligare_alembic.py
test/unit/schema/test_dialect.py
typings/alembic/__init__.pyi
typings/alembic/__main__.pyi
typings/alembic/command.pyi
typings/alembic/config.pyi
typings/alembic/context.pyi
typings/alembic/environment.pyi
typings/alembic/migration.pyi
typings/alembic/op.pyi
typings/alembic/autogenerate/__init__.pyi
typings/alembic/autogenerate/api.pyi
typings/alembic/autogenerate/compare.pyi
typings/alembic/autogenerate/render.pyi
typings/alembic/autogenerate/rewriter.pyi
typings/alembic/ddl/__init__.pyi
typings/alembic/ddl/_autogen.pyi
typings/alembic/ddl/base.pyi
typings/alembic/ddl/impl.pyi
typings/alembic/ddl/mssql.pyi
typings/alembic/ddl/mysql.pyi
typings/alembic/ddl/oracle.pyi
typings/alembic/ddl/postgresql.pyi
typings/alembic/ddl/sqlite.pyi
ligare_database-0.5.1.dist-info/METADATA
ligare_database-0.5.1.dist-info/WHEEL
ligare_database-0.5.1.dist-info/entry_points.txt
ligare_database-0.5.1.dist-info/top_level.txt
ligare_database-0.5.1.dist-info/RECORD
